neat/__init__.py
neat/activations.py
neat/aggregations.py
neat/attributes.py
neat/checkpoint.py
neat/config.py
neat/distributed.py
neat/genes.py
neat/genome.py
neat/graphs.py
neat/math_util.py
neat/parallel.py
neat/population.py
neat/reporting.py
neat/reproduction.py
neat/species.py
neat/stagnation.py
neat/statistics.py
neat/threaded.py
neat/ctrnn/__init__.py
neat/iznn/__init__.py
neat/nn/__init__.py
neat/nn/feed_forward.py
neat/nn/recurrent.py
ganariya_neat-0.96.0.dist-info/LICENSE
ganariya_neat-0.96.0.dist-info/METADATA
ganariya_neat-0.96.0.dist-info/WHEEL
ganariya_neat-0.96.0.dist-info/top_level.txt
ganariya_neat-0.96.0.dist-info/RECORD
