Metadata-Version: 2.1
Name: ganariya-neat
Version: 0.96.0
Summary: A NEAT (NeuroEvolution of Augmenting Topologies) implementation to ganariya research. 評価の位置を変更、エラーがあればおそらくこれが原因。
Home-page: https://github.com/Ganariya/neat-python
Author: cesar.gomes, mirrorballu2, ganariya
Author-email: nobody@nowhere.com
Maintainer: CodeReclaimers, LLC
Maintainer-email: alan@codereclaimers.com
License: BSD
Platform: UNKNOWN
Classifier: Development Status :: 4 - Beta
Classifier: Intended Audience :: Developers
Classifier: Intended Audience :: Education
Classifier: Intended Audience :: Science/Research
Classifier: License :: OSI Approved :: BSD License
Classifier: Operating System :: OS Independent
Classifier: Programming Language :: Python :: 2.7
Classifier: Programming Language :: Python :: 3.3
Classifier: Programming Language :: Python :: 3.4
Classifier: Programming Language :: Python :: 3.5
Classifier: Programming Language :: Python :: 3.6
Classifier: Programming Language :: Python :: Implementation :: PyPy
Classifier: Topic :: Scientific/Engineering
